ewatercycle/__init__.py
ewatercycle/_repr.py
ewatercycle/container.py
ewatercycle/forcing.py
ewatercycle/models.py
ewatercycle/parameter_sets.py
ewatercycle/py.typed
ewatercycle/shared.py
ewatercycle/util.py
ewatercycle/version.py
ewatercycle/_forcings/__init__.py
ewatercycle/_forcings/caravan.py
ewatercycle/_forcings/makkink.py
ewatercycle/analysis/__init__.py
ewatercycle/base/__init__.py
ewatercycle/base/forcing.py
ewatercycle/base/model.py
ewatercycle/base/parameter_set.py
ewatercycle/config/__init__.py
ewatercycle/esmvaltool/__init__.py
ewatercycle/esmvaltool/builder.py
ewatercycle/esmvaltool/datasets.py
ewatercycle/esmvaltool/missing.py
ewatercycle/esmvaltool/run.py
ewatercycle/esmvaltool/schema.py
ewatercycle/esmvaltool/search.py
ewatercycle/esmvaltool/diagnostic/__init__.py
ewatercycle/esmvaltool/diagnostic/copier.py
ewatercycle/observation/__init__.py
ewatercycle/observation/caravan.py
ewatercycle/observation/grdc.py
ewatercycle/observation/usgs.py
ewatercycle/testing/__init__.py
ewatercycle/testing/fake_models.py
ewatercycle/testing/fixtures.py
ewatercycle/testing/helpers.py
ewatercycle/testing/data/Rhine/Rhine.dbf
ewatercycle/testing/data/Rhine/Rhine.prj
ewatercycle/testing/data/Rhine/Rhine.qpj
ewatercycle/testing/data/Rhine/Rhine.shp
ewatercycle/testing/data/Rhine/Rhine.shx
ewatercycle-2.4.0.dist-info/METADATA
ewatercycle-2.4.0.dist-info/WHEEL
ewatercycle-2.4.0.dist-info/licenses/LICENSE
ewatercycle-2.4.0.dist-info/RECORD
