Metadata-Version: 2.3
Name: ewatercycle
Version: 2.4.0
Summary: A Python package for running and validating a hydrology model
Project-URL: Bug Tracker, https://github.com/eWaterCycle/ewatercycle/issues
Project-URL: Documentation, https://ewatercycle.readthedocs.io/
Project-URL: Homepage, https://www.ewatercycle.org/
Project-URL: Source Code, https://github.com/eWaterCycle/ewatercycle
Author-email: Stefan Verhoeven <s.verhoeven@esciencecenter.nl>
License: Apache-2.0
Keywords: BMI,FAIR,Geoscience,ewatercycle
Classifier: Development Status :: 5 - Production/Stable
Classifier: Intended Audience :: Developers
Classifier: License :: OSI Approved :: Apache Software License
Classifier: Natural Language :: English
Classifier: Programming Language :: Python :: 3
Classifier: Programming Language :: Python :: 3 :: Only
Classifier: Programming Language :: Python :: 3.10
Classifier: Programming Language :: Python :: 3.11
Classifier: Programming Language :: Python :: 3.12
Classifier: Topic :: Scientific/Engineering
Classifier: Topic :: Scientific/Engineering :: GIS
Classifier: Topic :: Scientific/Engineering :: Hydrology
Classifier: Typing :: Typed
Requires-Python: >=3.10
Requires-Dist: bmipy
Requires-Dist: cartopy
Requires-Dist: cftime>=1.6.2
Requires-Dist: fiona
Requires-Dist: fsspec
Requires-Dist: grpc4bmi>=0.4.0
Requires-Dist: hydrostats
Requires-Dist: matplotlib>=3.5.0
Requires-Dist: numpy
Requires-Dist: pandas
Requires-Dist: pydantic>=2
Requires-Dist: pyoos
Requires-Dist: pyopenssl>=24.0.0
Requires-Dist: python-dateutil
Requires-Dist: remotebmi
Requires-Dist: ruamel-yaml
Requires-Dist: shapely
Requires-Dist: xarray
Provides-Extra: dev
Requires-Dist: ipython; extra == 'dev'
Requires-Dist: mypy; extra == 'dev'
Requires-Dist: myst-nb; extra == 'dev'
Requires-Dist: pre-commit>=2.15.0; extra == 'dev'
Requires-Dist: pytest; extra == 'dev'
Requires-Dist: pytest-cov; extra == 'dev'
Requires-Dist: pytest-runner; extra == 'dev'
Requires-Dist: rich; extra == 'dev'
Requires-Dist: ruff; extra == 'dev'
Requires-Dist: sphinx; extra == 'dev'
Requires-Dist: sphinx-autoapi; extra == 'dev'
Requires-Dist: sphinx-copybutton; extra == 'dev'
Requires-Dist: sphinx-rtd-theme; extra == 'dev'
Requires-Dist: tomli; extra == 'dev'
Requires-Dist: types-python-dateutil; extra == 'dev'
Requires-Dist: types-pyyaml; extra == 'dev'
Requires-Dist: types-requests; extra == 'dev'
